optimization_course/lp_graphical_solution.py
optimization_course/simplex_method.py
optimization_course-0.2.1.dist-info/METADATA
optimization_course-0.2.1.dist-info/WHEEL
optimization_course-0.2.1.dist-info/RECORD
