Metadata-Version: 2.1
Name: optimization_course
Version: 0.2.1
Summary: 
Author: hatarhini
Author-email: hussein.tarhini@gmail.com
Requires-Python: >=3.10,<4.0
Classifier: Programming Language :: Python :: 3
Classifier: Programming Language :: Python :: 3.10
Classifier: Programming Language :: Python :: 3.11
Classifier: Programming Language :: Python :: 3.12
Requires-Dist: PuLP (>=2.9.0,<3.0.0)
Requires-Dist: matplotlib (>=3.9.2,<4.0.0)
Requires-Dist: openpyxl
Requires-Dist: pandas
Requires-Dist: scipy (>=1.7.3,<2.0.0)
